MANIFEST.in
setup.py
bin/make_config
config_maker/__init__.py
config_maker/maker.py
config_maker.egg-info/PKG-INFO
config_maker.egg-info/SOURCES.txt
config_maker.egg-info/dependency_links.txt
config_maker.egg-info/top_level.txt