Metadata-Version: 1.1
Name: config-maker
Version: 0.0.1
Summary: Create config files from environment
Home-page: https://github.com/i-kh/make_config_script
Author: Irina Kharitonova
Author-email: UNKNOWN
License: UNKNOWN
Download-URL: https://github.com/i-kh/make_config_script/archive/master.zip
Keywords: configs
Platform: UNKNOWN
